agent_dingo/__init__.py
agent_dingo/serve.py
agent_dingo/utils.py
agent_dingo/agent/__init__.py
agent_dingo/agent/agent.py
agent_dingo/agent/chat_context.py
agent_dingo/agent/docgen.py
agent_dingo/agent/function_descriptor.py
agent_dingo/agent/helpers.py
agent_dingo/agent/langchain.py
agent_dingo/agent/parser.py
agent_dingo/agent/registry.py
agent_dingo/core/blocks.py
agent_dingo/core/message.py
agent_dingo/core/output_parser.py
agent_dingo/core/state.py
agent_dingo/llm/gemini.py
agent_dingo/llm/litellm.py
agent_dingo/llm/llama_cpp.py
agent_dingo/llm/openai.py
agent_dingo/rag/base.py
agent_dingo/rag/prompt_modifiers.py
agent_dingo/rag/chunkers/__init__.py
agent_dingo/rag/chunkers/recursive.py
agent_dingo/rag/embedders/__init__.py
agent_dingo/rag/embedders/openai.py
agent_dingo/rag/embedders/sentence_transformer.py
agent_dingo/rag/readers/__init__.py
agent_dingo/rag/readers/list.py
agent_dingo/rag/readers/pdf.py
agent_dingo/rag/readers/web.py
agent_dingo/rag/readers/word.py
agent_dingo/rag/vector_stores/chromadb.py
agent_dingo/rag/vector_stores/qdrant.py
agent_dingo-1.0.0.dist-info/LICENSE
agent_dingo-1.0.0.dist-info/METADATA
agent_dingo-1.0.0.dist-info/WHEEL
agent_dingo-1.0.0.dist-info/top_level.txt
agent_dingo-1.0.0.dist-info/RECORD
