Metadata-Version: 2.1
Name: agent_dingo
Version: 1.0.0
Summary: A microframework for creating simple AI agents.
Author-email: Oleh Kostromin <kostromin97@gmail.com>, Iryna Kondrashchenko <iryna230520@gmail.com>
License: MIT
Classifier: Programming Language :: Python :: 3
Classifier: License :: OSI Approved :: MIT License
Classifier: Operating System :: OS Independent
Requires-Python: >=3.9
License-File: LICENSE
Requires-Dist: openai <2.0.0,>=1.25.0
Requires-Dist: docstring-parser <1.0.0,>=0.15.0
Requires-Dist: tenacity <9.0.0,>=8.2.0
Provides-Extra: chromadb
Requires-Dist: chromadb <1.0.0,>=0.5.0 ; extra == 'chromadb'
Provides-Extra: langchain
Requires-Dist: langchain <0.2.0,>=0.1.0 ; extra == 'langchain'
Provides-Extra: litellm
Requires-Dist: litellm <2.0.0,>=1.30.0 ; extra == 'litellm'
Provides-Extra: llama-cpp
Requires-Dist: llama-cpp-python <0.3.0,>=0.2.20 ; extra == 'llama-cpp'
Provides-Extra: qdrant
Requires-Dist: qdrant-client <2.0.0,>=1.9.0 ; extra == 'qdrant'
Provides-Extra: rag-default
Requires-Dist: PyPDF2 <4.0.0,>=3.0.0 ; extra == 'rag-default'
Requires-Dist: beautifulsoup4 <5.0.0,>=4.12.0 ; extra == 'rag-default'
Requires-Dist: requests <3.0.0,>=2.26.0 ; extra == 'rag-default'
Requires-Dist: python-docx <2.0.0,>=1.0.0 ; extra == 'rag-default'
Provides-Extra: sentence-transformers
Requires-Dist: sentence-transformers <3.0.0,>=2.3.0 ; extra == 'sentence-transformers'
Provides-Extra: server
Requires-Dist: fastapi <1.0.0,>=0.105.0 ; extra == 'server'
Requires-Dist: uvicorn <1.0.0,>=0.20.0 ; extra == 'server'
Provides-Extra: vertexai
Requires-Dist: google-cloud-aiplatform <2.0.0,>=1.40.0 ; extra == 'vertexai'
